pullcite/__init__.py
pullcite/core/__init__.py
pullcite/core/chunk.py
pullcite/core/chunker.py
pullcite/core/document.py
pullcite/core/evidence.py
pullcite/core/paths.py
pullcite/core/result.py
pullcite/embeddings/__init__.py
pullcite/embeddings/base.py
pullcite/embeddings/cache.py
pullcite/embeddings/local.py
pullcite/embeddings/openai.py
pullcite/embeddings/voyage.py
pullcite/llms/__init__.py
pullcite/llms/anthropic.py
pullcite/llms/base.py
pullcite/llms/openai.py
pullcite/retrieval/__init__.py
pullcite/retrieval/base.py
pullcite/retrieval/chroma.py
pullcite/retrieval/memory.py
pullcite/retrieval/pgvector.py
pullcite/schema/__init__.py
pullcite/schema/base.py
pullcite/schema/extractor.py
pullcite/schema/fields.py
pullcite/search/__init__.py
pullcite/search/base.py
pullcite/search/bm25.py
pullcite/search/hybrid.py
pullcite-0.2.7.dist-info/METADATA
pullcite-0.2.7.dist-info/WHEEL
pullcite-0.2.7.dist-info/licenses/LICENSE
pullcite-0.2.7.dist-info/RECORD
