Metadata-Version: 2.4
Name: pullcite
Version: 0.2.7
Summary: Evidence-backed structured extraction from documents
Project-URL: Homepage, https://pullcite.com
Project-URL: Repository, https://github.com/usercando/pullcite
Project-URL: Documentation, https://github.com/usercando/pullcite#readme
Author-email: UserCanDo <dev@usercando.com>
Maintainer-email: Dike Kalu <dike@usercando.com>
License-Expression: MIT
License-File: LICENSE
Keywords: evidence,extraction,llm,pdf,pydantic,structured-output
Classifier: Development Status :: 3 - Alpha
Classifier: Intended Audience :: Developers
Classifier: License :: OSI Approved :: MIT License
Classifier: Programming Language :: Python :: 3
Classifier: Programming Language :: Python :: 3.10
Classifier: Programming Language :: Python :: 3.11
Classifier: Programming Language :: Python :: 3.12
Classifier: Topic :: Scientific/Engineering :: Artificial Intelligence
Classifier: Topic :: Text Processing :: General
Requires-Python: >=3.11
Requires-Dist: black>=25.12.0
Requires-Dist: numpy>=1.24.0
Requires-Dist: pydantic>=2.0
Provides-Extra: all
Requires-Dist: anthropic>=0.30.0; extra == 'all'
Requires-Dist: chromadb>=0.4.0; extra == 'all'
Requires-Dist: docling>=2.0.0; extra == 'all'
Requires-Dist: openai>=1.0.0; extra == 'all'
Requires-Dist: pgvector>=0.2.0; extra == 'all'
Requires-Dist: psycopg2-binary>=2.9.0; extra == 'all'
Requires-Dist: sentence-transformers>=2.2.0; extra == 'all'
Requires-Dist: tantivy>=0.22.0; extra == 'all'
Requires-Dist: voyageai>=0.2.0; extra == 'all'
Provides-Extra: anthropic
Requires-Dist: anthropic>=0.30.0; extra == 'anthropic'
Provides-Extra: chroma
Requires-Dist: chromadb>=0.4.0; extra == 'chroma'
Provides-Extra: dev
Requires-Dist: faker>=40.0.0; extra == 'dev'
Requires-Dist: mypy>=1.0.0; extra == 'dev'
Requires-Dist: pytest-cov>=4.0.0; extra == 'dev'
Requires-Dist: pytest>=7.0.0; extra == 'dev'
Requires-Dist: ruff>=0.1.0; extra == 'dev'
Provides-Extra: docling
Requires-Dist: docling>=2.0.0; extra == 'docling'
Provides-Extra: local
Requires-Dist: sentence-transformers>=2.2.0; extra == 'local'
Provides-Extra: openai
Requires-Dist: openai>=1.0.0; extra == 'openai'
Provides-Extra: pgvector
Requires-Dist: pgvector>=0.2.0; extra == 'pgvector'
Requires-Dist: psycopg2-binary>=2.9.0; extra == 'pgvector'
Provides-Extra: tantivy
Requires-Dist: tantivy>=0.22.0; extra == 'tantivy'
Provides-Extra: voyage
Requires-Dist: voyageai>=0.2.0; extra == 'voyage'
